{"category": {"url": "http://pokeapi.co/api/v2/item-category/18/", "name": "species-specific"}, "name": "deep-sea-scale", "fling_effect": null, "effect_entries": [{"short_effect": "Doubles Clamperl's Special Defense. Traded on a Clamperl: Holder evolves into Gorebyss.", "effect": "Held by Clamperl: Doubles the holder's Special Defense.  Evolves the holder into Gorebyss when traded.", "language": {"url": "http://pokeapi.co/api/v2/language/9/", "name": "en"}}], "held_by_pokemon": [{"pokemon": {"url": "http://pokeapi.co/api/v2/pokemon/170/", "name": "chinchou"}, "version_details": [{"version": {"url": "http://pokeapi.co/api/v2/version/24/", "name": "y"}, "rarity": 5}, {"version": {"url": "http://pokeapi.co/api/v2/version/23/", "name": "x"}, "rarity": 5}, {"version": {"url": "http://pokeapi.co/api/v2/version/22/", "name": "white-2"}, "rarity": 5}, {"version": {"url": "http://pokeapi.co/api/v2/version/21/", "name": "black-2"}, "rarity": 5}, {"version": {"url": "http://pokeapi.co/api/v2/version/18/", "name": "white"}, "rarity": 5}, {"version": {"url": "http://pokeapi.co/api/v2/version/17/", "name": "black"}, "rarity": 5}, {"version": {"url": "http://pokeapi.co/api/v2/version/16/", "name": "soulsilver"}, "rarity": 5}, {"version": {"url": "http://pokeapi.co/api/v2/version/15/", "name": "heartgold"}, "rarity": 5}, {"version": {"url": "http://pokeapi.co/api/v2/version/14/", "name": "platinum"}, "rarity": 5}, {"version": {"url": "http://pokeapi.co/api/v2/version/13/", "name": "pearl"}, "rarity": 5}, {"version": {"url": "http://pokeapi.co/api/v2/version/12/", "name": "diamond"}, "rarity": 5}]}, {"pokemon": {"url": "http://pokeapi.co/api/v2/pokemon/171/", "name": "lanturn"}, "version_details": [{"version": {"url": "http://pokeapi.co/api/v2/version/24/", "name": "y"}, "rarity": 5}, {"version": {"url": "http://pokeapi.co/api/v2/version/23/", "name": "x"}, "rarity": 5}, {"version": {"url": "http://pokeapi.co/api/v2/version/22/", "name": "white-2"}, "rarity": 5}, {"version": {"url": "http://pokeapi.co/api/v2/version/21/", "name": "black-2"}, "rarity": 5}, {"version": {"url": "http://pokeapi.co/api/v2/version/18/", "name": "white"}, "rarity": 5}, {"version": {"url": "http://pokeapi.co/api/v2/version/17/", "name": "black"}, "rarity": 5}, {"version": {"url": "http://pokeapi.co/api/v2/version/16/", "name": "soulsilver"}, "rarity": 5}, {"version": {"url": "http://pokeapi.co/api/v2/version/15/", "name": "heartgold"}, "rarity": 5}, {"version": {"url": "http://pokeapi.co/api/v2/version/14/", "name": "platinum"}, "rarity": 5}, {"version": {"url": "http://pokeapi.co/api/v2/version/13/", "name": "pearl"}, "rarity": 5}, {"version": {"url": "http://pokeapi.co/api/v2/version/12/", "name": "diamond"}, "rarity": 5}]}, {"pokemon": {"url": "http://pokeapi.co/api/v2/pokemon/368/", "name": "gorebyss"}, "version_details": [{"version": {"url": "http://pokeapi.co/api/v2/version/24/", "name": "y"}, "rarity": 5}, {"version": {"url": "http://pokeapi.co/api/v2/version/23/", "name": "x"}, "rarity": 5}, {"version": {"url": "http://pokeapi.co/api/v2/version/22/", "name": "white-2"}, "rarity": 5}, {"version": {"url": "http://pokeapi.co/api/v2/version/21/", "name": "black-2"}, "rarity": 5}, {"version": {"url": "http://pokeapi.co/api/v2/version/18/", "name": "white"}, "rarity": 5}, {"version": {"url": "http://pokeapi.co/api/v2/version/17/", "name": "black"}, "rarity": 5}, {"version": {"url": "http://pokeapi.co/api/v2/version/16/", "name": "soulsilver"}, "rarity": 5}, {"version": {"url": "http://pokeapi.co/api/v2/version/15/", "name": "heartgold"}, "rarity": 5}, {"version": {"url": "http://pokeapi.co/api/v2/version/14/", "name": "platinum"}, "rarity": 5}, {"version": {"url": "http://pokeapi.co/api/v2/version/13/", "name": "pearl"}, "rarity": 5}, {"version": {"url": "http://pokeapi.co/api/v2/version/12/", "name": "diamond"}, "rarity": 5}]}, {"pokemon": {"url": "http://pokeapi.co/api/v2/pokemon/369/", "name": "relicanth"}, "version_details": [{"version": {"url": "http://pokeapi.co/api/v2/version/24/", "name": "y"}, "rarity": 5}, {"version": {"url": "http://pokeapi.co/api/v2/version/23/", "name": "x"}, "rarity": 5}, {"version": {"url": "http://pokeapi.co/api/v2/version/22/", "name": "white-2"}, "rarity": 5}, {"version": {"url": "http://pokeapi.co/api/v2/version/21/", "name": "black-2"}, "rarity": 5}, {"version": {"url": "http://pokeapi.co/api/v2/version/18/", "name": "white"}, "rarity": 5}, {"version": {"url": "http://pokeapi.co/api/v2/version/17/", "name": "black"}, "rarity": 5}, {"version": {"url": "http://pokeapi.co/api/v2/version/16/", "name": "soulsilver"}, "rarity": 5}, {"version": {"url": "http://pokeapi.co/api/v2/version/15/", "name": "heartgold"}, "rarity": 5}, {"version": {"url": "http://pokeapi.co/api/v2/version/14/", "name": "platinum"}, "rarity": 5}, {"version": {"url": "http://pokeapi.co/api/v2/version/13/", "name": "pearl"}, "rarity": 5}, {"version": {"url": "http://pokeapi.co/api/v2/version/12/", "name": "diamond"}, "rarity": 5}]}, {"pokemon": {"url": "http://pokeapi.co/api/v2/pokemon/10016/", "name": "basculin-blue-striped"}, "version_details": [{"version": {"url": "http://pokeapi.co/api/v2/version/24/", "name": "y"}, "rarity": 5}, {"version": {"url": "http://pokeapi.co/api/v2/version/23/", "name": "x"}, "rarity": 5}, {"version": {"url": "http://pokeapi.co/api/v2/version/22/", "name": "white-2"}, "rarity": 5}, {"version": {"url": "http://pokeapi.co/api/v2/version/21/", "name": "black-2"}, "rarity": 5}, {"version": {"url": "http://pokeapi.co/api/v2/version/18/", "name": "white"}, "rarity": 5}, {"version": {"url": "http://pokeapi.co/api/v2/version/17/", "name": "black"}, "rarity": 5}]}], "baby_trigger_for": null, "game_indices": [{"generation": {"url": "http://pokeapi.co/api/v2/generation/6/", "name": "generation-vi"}, "game_index": 227}, {"generation": {"url": "http://pokeapi.co/api/v2/generation/5/", "name": "generation-v"}, "game_index": 227}, {"generation": {"url": "http://pokeapi.co/api/v2/generation/4/", "name": "generation-iv"}, "game_index": 227}, {"generation": {"url": "http://pokeapi.co/api/v2/generation/3/", "name": "generation-iii"}, "game_index": 193}], "cost": 200, "names": [{"name": "Deep Sea Scale", "language": {"url": "http://pokeapi.co/api/v2/language/9/", "name": "en"}}, {"name": "Squamabissi", "language": {"url": "http://pokeapi.co/api/v2/language/8/", "name": "it"}}, {"name": "Escama Marina", "language": {"url": "http://pokeapi.co/api/v2/language/7/", "name": "es"}}, {"name": "Abyssplatte", "language": {"url": "http://pokeapi.co/api/v2/language/6/", "name": "de"}}, {"name": "Écaille Océan", "language": {"url": "http://pokeapi.co/api/v2/language/5/", "name": "fr"}}, {"name": "심해의비늘", "language": {"url": "http://pokeapi.co/api/v2/language/3/", "name": "ko"}}, {"name": "しんかいのウロコ", "language": {"url": "http://pokeapi.co/api/v2/language/1/", "name": "ja"}}], "id": 204, "attributes": [{"url": "http://pokeapi.co/api/v2/item-attribute/5/", "name": "holdable"}], "flavor_text_entries": [{"text": "パールルに　持たせると\n特防が　あがる　ウロコ。\nうすい　ピンク色に　光る。", "version_group": {"url": "http://pokeapi.co/api/v2/version-group/15/", "name": "x-y"}, "language": {"url": "http://pokeapi.co/api/v2/language/11/", "name": "ja-kanji"}}, {"text": "An item to be held by Clamperl.\nThis scale shines with a faint pink and\nraises the holder’s Sp. Def stat.", "version_group": {"url": "http://pokeapi.co/api/v2/version-group/15/", "name": "x-y"}, "language": {"url": "http://pokeapi.co/api/v2/language/9/", "name": "en"}}, {"text": "Strumento da dare a Clamperl.\nSquama dai bagliori rosei che aumenta\nla Difesa Speciale.", "version_group": {"url": "http://pokeapi.co/api/v2/version-group/15/", "name": "x-y"}, "language": {"url": "http://pokeapi.co/api/v2/language/8/", "name": "it"}}, {"text": "Pico largo y afilado que aumenta la potencia de\nlos movimientos de tipo Volador. Debe llevarlo un\nPokémon.", "version_group": {"url": "http://pokeapi.co/api/v2/version-group/15/", "name": "x-y"}, "language": {"url": "http://pokeapi.co/api/v2/language/7/", "name": "es"}}, {"text": "Ein Item, das von Perlu getragen werden kann.\nEs schimmert pink und hebt die\nSpezial-Verteidigung.", "version_group": {"url": "http://pokeapi.co/api/v2/version-group/15/", "name": "x-y"}, "language": {"url": "http://pokeapi.co/api/v2/language/6/", "name": "de"}}, {"text": "Objet à faire tenir à Coquiperl.\nUne écaille de couleur rose qui augmente\nsa Défense Spéciale.", "version_group": {"url": "http://pokeapi.co/api/v2/version-group/15/", "name": "x-y"}, "language": {"url": "http://pokeapi.co/api/v2/language/5/", "name": "fr"}}, {"text": "진주몽에게 지니게 하면\n특수방어가 올라가는 비늘.\n연한 분홍색으로 빛난다.", "version_group": {"url": "http://pokeapi.co/api/v2/version-group/15/", "name": "x-y"}, "language": {"url": "http://pokeapi.co/api/v2/language/3/", "name": "ko"}}, {"text": "パールルに　もたせると\nとくぼうが　あがる　ウロコ。\nうすい　ピンクいろに　ひかる。", "version_group": {"url": "http://pokeapi.co/api/v2/version-group/15/", "name": "x-y"}, "language": {"url": "http://pokeapi.co/api/v2/language/1/", "name": "ja"}}, {"text": "An item to be held by Clamperl.\nA scale that shines a faint pink, it\nraises the Sp. Def stat.", "version_group": {"url": "http://pokeapi.co/api/v2/version-group/14/", "name": "black-2-white-2"}, "language": {"url": "http://pokeapi.co/api/v2/language/9/", "name": "en"}}, {"text": "An item to be held by Clamperl.\nA scale that shines a faint pink, it\nraises the Sp. Def stat.", "version_group": {"url": "http://pokeapi.co/api/v2/version-group/11/", "name": "black-white"}, "language": {"url": "http://pokeapi.co/api/v2/language/9/", "name": "en"}}, {"text": "Objet à faire tenir à Coquiperl.\nÉcaille de couleur rose montant\nsa Défense Spéciale.", "version_group": {"url": "http://pokeapi.co/api/v2/version-group/11/", "name": "black-white"}, "language": {"url": "http://pokeapi.co/api/v2/language/5/", "name": "fr"}}, {"text": "An item to be held by CLAMPERL.\nA scale that shines a faint pink, it\nraises the Sp. Def stat.", "version_group": {"url": "http://pokeapi.co/api/v2/version-group/10/", "name": "heartgold-soulsilver"}, "language": {"url": "http://pokeapi.co/api/v2/language/9/", "name": "en"}}, {"text": "An item to be held by CLAMPERL.\nA scale that shines a faint pink, it\nraises the Sp. Def stat.", "version_group": {"url": "http://pokeapi.co/api/v2/version-group/9/", "name": "platinum"}, "language": {"url": "http://pokeapi.co/api/v2/language/9/", "name": "en"}}, {"text": "An item to be held by CLAMPERL.\nA scale that shines a faint pink, it\nraises the Sp. Def stat.", "version_group": {"url": "http://pokeapi.co/api/v2/version-group/8/", "name": "diamond-pearl"}, "language": {"url": "http://pokeapi.co/api/v2/language/9/", "name": "en"}}, {"text": "An item to be held by a POKéMON.\nA scale that shines a faint pink.\nIt raises the SP. DEF stat.", "version_group": {"url": "http://pokeapi.co/api/v2/version-group/7/", "name": "firered-leafgreen"}, "language": {"url": "http://pokeapi.co/api/v2/language/9/", "name": "en"}}, {"text": "A hold item that\nraises the SP. DEF\nof CLAMPERL.", "version_group": {"url": "http://pokeapi.co/api/v2/version-group/6/", "name": "emerald"}, "language": {"url": "http://pokeapi.co/api/v2/language/9/", "name": "en"}}, {"text": "A hold item that\nraises the SP. DEF\nof CLAMPERL.", "version_group": {"url": "http://pokeapi.co/api/v2/version-group/5/", "name": "ruby-sapphire"}, "language": {"url": "http://pokeapi.co/api/v2/language/9/", "name": "en"}}], "sprites": {"default": "https://raw.githubusercontent.com/PokeAPI/sprites/master/sprites/items/deep-sea-scale.png"}, "machines": [], "fling_power": 30}