{"category": {"url": "http://pokeapi.co/api/v2/item-category/10/", "name": "evolution"}, "name": "whipped-dream", "fling_effect": null, "effect_entries": [], "held_by_pokemon": [], "baby_trigger_for": null, "game_indices": [{"generation": {"url": "http://pokeapi.co/api/v2/generation/6/", "name": "generation-vi"}, "game_index": 646}], "cost": 0, "names": [{"name": "Whipped Dream", "language": {"url": "http://pokeapi.co/api/v2/language/9/", "name": "en"}}, {"name": "Dolcespuma", "language": {"url": "http://pokeapi.co/api/v2/language/8/", "name": "it"}}, {"name": "Dulce de Nata", "language": {"url": "http://pokeapi.co/api/v2/language/7/", "name": "es"}}, {"name": "Sahnehäubchen", "language": {"url": "http://pokeapi.co/api/v2/language/6/", "name": "de"}}, {"name": "Chantibonbon", "language": {"url": "http://pokeapi.co/api/v2/language/5/", "name": "fr"}}, {"name": "휘핑팝", "language": {"url": "http://pokeapi.co/api/v2/language/3/", "name": "ko"}}, {"name": "ホイップポップ", "language": {"url": "http://pokeapi.co/api/v2/language/1/", "name": "ja"}}], "id": 686, "attributes": [], "flavor_text_entries": [{"text": "ふんわり　ふわふわに　泡立てた\nほんのり　甘い　クリーム。\nある　ポケモンが　好んでいる。", "version_group": {"url": "http://pokeapi.co/api/v2/version-group/15/", "name": "x-y"}, "language": {"url": "http://pokeapi.co/api/v2/language/11/", "name": "ja-kanji"}}, {"text": "A soft and sweet treat made of fluffy,\npuffy, whipped and whirled cream.\nIt’s loved by a certain Pokémon.", "version_group": {"url": "http://pokeapi.co/api/v2/version-group/15/", "name": "x-y"}, "language": {"url": "http://pokeapi.co/api/v2/language/9/", "name": "en"}}, {"text": "Una spuma soffice, delicata e leggermente dolce.\nPiace a un Pokémon in particolare.", "version_group": {"url": "http://pokeapi.co/api/v2/version-group/15/", "name": "x-y"}, "language": {"url": "http://pokeapi.co/api/v2/language/8/", "name": "it"}}, {"text": "Una de las misteriosas Megapiedras. Permite\nmegaevolucionar a Medicham en combate.", "version_group": {"url": "http://pokeapi.co/api/v2/version-group/15/", "name": "x-y"}, "language": {"url": "http://pokeapi.co/api/v2/language/7/", "name": "es"}}, {"text": "Ein lockeres, leicht süßliches Häubchen\naus Schlagsahne, das bei einer bestimmten\nPokémon-Art sehr beliebt ist.", "version_group": {"url": "http://pokeapi.co/api/v2/version-group/15/", "name": "x-y"}, "language": {"url": "http://pokeapi.co/api/v2/language/6/", "name": "de"}}, {"text": "Une crème sucrée qui fond dans la bouche,\nlégère comme un nuage. Elle est appréciée\nd’un certain Pokémon.", "version_group": {"url": "http://pokeapi.co/api/v2/version-group/15/", "name": "x-y"}, "language": {"url": "http://pokeapi.co/api/v2/language/5/", "name": "fr"}}, {"text": "풍성하게 거품을 낸\n살짝 달콤한 크림.\n어떤 포켓몬이 좋아한다.", "version_group": {"url": "http://pokeapi.co/api/v2/version-group/15/", "name": "x-y"}, "language": {"url": "http://pokeapi.co/api/v2/language/3/", "name": "ko"}}, {"text": "ふんわり　ふわふわに　あわだてた\nほんのり　あまい　クリーム。\nある　ポケモンが　このんでいる。", "version_group": {"url": "http://pokeapi.co/api/v2/version-group/15/", "name": "x-y"}, "language": {"url": "http://pokeapi.co/api/v2/language/1/", "name": "ja"}}], "sprites": {"default": "https://raw.githubusercontent.com/PokeAPI/sprites/master/sprites/items/whipped-dream.png"}, "machines": [], "fling_power": null}