{"move_learn_methods": [{"url": "http://pokeapi.co/api/v2/move-learn-method/1/", "name": "level-up"}, {"url": "http://pokeapi.co/api/v2/move-learn-method/2/", "name": "egg"}, {"url": "http://pokeapi.co/api/v2/move-learn-method/3/", "name": "tutor"}, {"url": "http://pokeapi.co/api/v2/move-learn-method/4/", "name": "machine"}, {"url": "http://pokeapi.co/api/v2/move-learn-method/6/", "name": "light-ball-egg"}, {"url": "http://pokeapi.co/api/v2/move-learn-method/10/", "name": "form-change"}], "name": "omega-ruby-alpha-sapphire", "versions": [{"url": "http://pokeapi.co/api/v2/version/25/", "name": "omega-ruby"}, {"url": "http://pokeapi.co/api/v2/version/26/", "name": "alpha-sapphire"}], "generation": {"url": "http://pokeapi.co/api/v2/generation/6/", "name": "generation-vi"}, "order": 16, "regions": [{"url": "http://pokeapi.co/api/v2/region/3/", "name": "hoenn"}], "pokedexes": [{"url": "http://pokeapi.co/api/v2/pokedex/15/", "name": "updated-hoenn"}], "id": 16}