{"name": "unova-route-15", "region": {"url": "http://pokeapi.co/api/v2/region/5/", "name": "unova"}, "game_indices": [{"generation": {"url": "http://pokeapi.co/api/v2/generation/5/", "name": "generation-v"}, "game_index": 28}, {"generation": {"url": "http://pokeapi.co/api/v2/generation/5/", "name": "generation-v"}, "game_index": 102}], "names": [{"name": "Route 15", "language": {"url": "http://pokeapi.co/api/v2/language/9/", "name": "en"}}, {"name": "Route 15", "language": {"url": "http://pokeapi.co/api/v2/language/5/", "name": "fr"}}, {"name": "１５番道路", "language": {"url": "http://pokeapi.co/api/v2/language/1/", "name": "ja"}}], "id": 370, "areas": [{"url": "http://pokeapi.co/api/v2/location-area/650/", "name": "unova-route-15-area"}]}