{"is_battle_only": false, "form_order": 20, "is_mega": false, "form_names": [{"name": "Poké Ball Pattern", "language": {"url": "http://pokeapi.co/api/v2/language/9/", "name": "en"}}, {"name": "Motivo Poké Ball", "language": {"url": "http://pokeapi.co/api/v2/language/8/", "name": "it"}}, {"name": "Motivo Poké Ball", "language": {"url": "http://pokeapi.co/api/v2/language/7/", "name": "es"}}, {"name": "Pokéball-Muster", "language": {"url": "http://pokeapi.co/api/v2/language/6/", "name": "de"}}, {"name": "Motif Poké Ball", "language": {"url": "http://pokeapi.co/api/v2/language/5/", "name": "fr"}}, {"name": "볼의 모양", "language": {"url": "http://pokeapi.co/api/v2/language/3/", "name": "ko"}}, {"name": "ボールのもよう", "language": {"url": "http://pokeapi.co/api/v2/language/1/", "name": "ja"}}], "version_group": {"url": "http://pokeapi.co/api/v2/version-group/15/", "name": "x-y"}, "is_default": false, "names": [{"name": "Poké Ball Vivillon", "language": {"url": "http://pokeapi.co/api/v2/language/9/", "name": "en"}}, {"name": "Prismillon Poké Ball", "language": {"url": "http://pokeapi.co/api/v2/language/5/", "name": "fr"}}], "id": 10162, "form_name": "poke-ball", "order": 806, "pokemon": {"url": "http://pokeapi.co/api/v2/pokemon/666/", "name": "vivillon"}, "sprites": {"front_default": null, "back_shiny": null, "front_shiny": null, "back_default": null}, "name": "vivillon-poke-ball"}